{"lmjf34.1610:pep":{"exact":[["LmjF34.1610:pep",0,"LmjF.34.1610","LmjF.34",726852,728847]],"prefix":[]},"lmjf.25.t0940":{"exact":[["LmjF.25.T0940",1,"LmjF.25.T0940","LmjF.25",355106,357294]],"prefix":[]},"lmjf10.0930:pseudogenic_transcript:p":{"exact":[],"prefix":["LmjF10.0930:pseudogenic_transcript:pep"]},"12311831":{"exact":[["12311831",0,"LmjF.04.1050","LmjF.04",398242,399313]],"prefix":[]},"lmjf.35.t105":{"exact":[],"prefix":["LmjF.35.T1050"]},"lmjf.09.trnaarg.01":{"exact":[["LmjF.09.TRNAARG.01",0,"LmjF.09.TRNAARG.01","LmjF.09",418947,419019]],"prefix":[]},"lmjf.35.4700":{"exact":[["LmjF.35.4700",0,"LmjF.35.4700","LmjF.35",1854060,1855503]],"prefix":[]},"chr16_tmp.0910":{"exact":[["CHR16_tmp.0910",0,"LmjF.16.0910","LmjF.16",336765,337290]],"prefix":[]},"lmjf28.1470:mrna":{"exact":[["LmjF28.1470:mRNA",0,"LmjF.28.1470","LmjF.28",554475,555339]],"prefix":[]},"lmjf22.snorna.0014:snorna":{"exact":[["LmjF22.snoRNA.0014:snoRNA",0,"LmjF.22.snoRNA0014","LmjF.22",589080,589136]],"prefix":[]},"lmjf30.2440:p":{"exact":[],"prefix":["LmjF30.2440:pep"]},"lmjf33.2440:mr":{"exact":[],"prefix":["LmjF33.2440:mRNA"]},"lmjf30.2900:pe":{"exact":[],"prefix":["LmjF30.2900:pep"]},"3225005":{"exact":[],"prefix":["322500556","322500592","322500564"]},"lmjf26.2680:mrn":{"exact":[],"prefix":["LmjF26.2680:mRNA"]},"lmjf26.snorna.0172:":{"exact":[],"prefix":["LmjF26.snoRNA.0172:snoRNA"]},"lmjf.09.0660":{"exact":[["LmjF.09.0660",0,"LmjF.09.0660","LmjF.09",266607,267666]],"prefix":[]},"lmjf26.snorna.0135":{"exact":[],"prefix":["LmjF26.snoRNA.0135:snoRNA"]},"lmjf27.rrna.52:":{"exact":[],"prefix":["LmjF27.rRNA.52:rRNA"]},"lmjf.34.t218":{"exact":[],"prefix":["LmjF.34.T2180","LmjF.34.T2185"]},"lmjf09.1350:pep":{"exact":[["LmjF09.1350:pep",0,"LmjF.09.1350","LmjF.09",520577,521156]],"prefix":[]},"hsp83-3":{"exact":[["HSP83-3",0,"LmjF.33.0316","LmjF.33",121169,123275]],"prefix":[]},"68126837":{"exact":[["68126837",0,"LmjF.25.0180","LmjF.25",53231,56381]],"prefix":[]},"68127251":{"exact":[["68127251",0,"LmjF.26.1755","LmjF.26",643202,644348]],"prefix":[]},"lmjf20.1010:mr":{"exact":[],"prefix":["LmjF20.1010:mRNA"]},"lmjf30.0370":{"exact":[["LmjF30.0370",0,"LmjF.30.0370","LmjF.30",118933,120166]],"prefix":["LmjF30.0370:mRNA","LmjF30.0370:pep"]},"lmjf30.083":{"exact":[],"prefix":["LmjF30.0830:pep","LmjF30.0830","LmjF30.0830:mRNA"]},"lmjf.34.412":{"exact":[],"prefix":["LmjF.34.4120"]},"lmjf.29.141":{"exact":[],"prefix":["LmjF.29.1410"]},"lmjf31.2170:p":{"exact":[],"prefix":["LmjF31.2170:pep"]},"lmjf.36.157":{"exact":[],"prefix":["LmjF.36.1570"]},"lmjf05.snorna.0071:snorna":{"exact":[["LmjF05.snoRNA.0071:snoRNA",0,"LmjF.05.snoRNA0071","LmjF.05",448545,448830]],"prefix":[]},"lmjf28.0890:mr":{"exact":[],"prefix":["LmjF28.0890:mRNA"]},"lmjf36.snorna.0063:snor":{"exact":[],"prefix":["LmjF36.snoRNA.0063:snoRNA"]},"lmjf.32.0240":{"exact":[["LmjF.32.0240",0,"LmjF.32.0240","LmjF.32",75407,78665]],"prefix":[]},"lmjf11.065":{"exact":[],"prefix":["LmjF11.0650","LmjF11.0650:pep","LmjF11.0650:mRNA"]},"lmjf10.0930:pseudogenic_transcrip":{"exact":[],"prefix":["LmjF10.0930:pseudogenic_transcript","LmjF10.0930:pseudogenic_transcript:pep"]},"38343962":{"exact":[["38343962",0,"LmjF.33.0240","LmjF.33",75086,76439]],"prefix":[]},"389593317":{"exact":[["389593317",0,"LmjF.27.1050","LmjF.27",447296,449297]],"prefix":[]}}