{"lmjf22.0490:mrna":{"exact":[["LmjF22.0490:mRNA",0,"LmjF.22.0490","LmjF.22",191982,194154]],"prefix":[]},"lmjf28.2900:mrna":{"exact":[["LmjF28.2900:mRNA",0,"LmjF.28.2900","LmjF.28",1102801,1104403]],"prefix":[]},"lmjf21.0830:mrn":{"exact":[],"prefix":["LmjF21.0830:mRNA"]},"lm14cs1c1.1":{"exact":[["LM14Cs1C1.1",0,"LmjF.14.snoRNA0005","LmjF.14",367891,368003]],"prefix":[]},"lmjf05.snorna.0020":{"exact":[],"prefix":["LmjF05.snoRNA.0020:snoRNA"]},"lmjf.27.rrna.4":{"exact":[],"prefix":["LmjF.27.rRNA.43","LmjF.27.rRNA.44","LmjF.27.rRNA.45","LmjF.27.rRNA.46","LmjF.27.rRNA.47","LmjF.27.rRNA.48","LmjF.27.rRNA.49","LmjF.27.rRNA.40","LmjF.27.rRNA.41","LmjF.27.rRNA.42"]},"157869676":{"exact":[["157869676",0,"LmjF.23.1665","LmjF.23",246926,247637]],"prefix":[]},"76363655":{"exact":[["76363655",0,"LmjF.04.0280","LmjF.04",90976,97258]],"prefix":[]},"lmjf01.0180:":{"exact":[],"prefix":["LmjF01.0180:pep","LmjF01.0180:mRNA"]},"lmjf36.2090:p":{"exact":[],"prefix":["LmjF36.2090:pep"]},"lmjf.24.0300":{"exact":[["LmjF.24.0300",0,"LmjF.24.0300","LmjF.24",84000,89361]],"prefix":[]},"lmjf15.snorna.0003:s":{"exact":[],"prefix":["LmjF15.snoRNA.0003:snoRNA"]},"lmjf23.snorna.0003:s":{"exact":[],"prefix":["LmjF23.snoRNA.0003:snoRNA"]},"lmjf30.1160:mrn":{"exact":[],"prefix":["LmjF30.1160:mRNA"]},"lmjf.35.024":{"exact":[],"prefix":["LmjF.35.0240"]},"lmjf33.2000:mrna":{"exact":[["LmjF33.2000:mRNA",0,"LmjF.33.2000","LmjF.33",891471,891819]],"prefix":[]},"lmjf33.1190:pep":{"exact":[["LmjF33.1190:pep",0,"LmjF.33.1190","LmjF.33",553664,556319]],"prefix":[]},"lmjf.23.t045":{"exact":[],"prefix":["LmjF.23.T0450","LmjF.23.T0452","LmjF.23.T0454"]},"lmjf.14.t0730":{"exact":[["LmjF.14.T0730",1,"LmjF.14.T0730","LmjF.14",277453,281600]],"prefix":[]},"chr28_tmp.221":{"exact":[],"prefix":["CHR28_tmp.2210"]},"lmjf.36.t4050":{"exact":[["LmjF.36.T4050",1,"LmjF.36.T4050","LmjF.36",1546219,1547715]],"prefix":[]},"lmjf09.0380":{"exact":[["LmjF09.0380",0,"LmjF.09.0380","LmjF.09",153990,155085]],"prefix":["LmjF09.0380:pep","LmjF09.0380:mRNA"]},"fatty acid thiokinase (long chai":{"exact":[],"prefix":["fatty acid thiokinase (long chain)"]},"lmjf25.1440:mrna":{"exact":[["LmjF25.1440:mRNA",0,"LmjF.25.1440","LmjF.25",565849,567379]],"prefix":[]},"lmjf19.0430:mr":{"exact":[],"prefix":["LmjF19.0430:mRNA"]},"lmjf29.2610":{"exact":[["LmjF29.2610",0,"LmjF.29.2610","LmjF.29",1124683,1126840]],"prefix":["LmjF29.2610:mRNA","LmjF29.2610:pep"]},"lmjf26.1250:pe":{"exact":[],"prefix":["LmjF26.1250:pep"]},"157873629":{"exact":[["157873629",0,"LmjF.32.0080","LmjF.32",23829,25095]],"prefix":[]},"lmjf26.snorna.0452:snor":{"exact":[],"prefix":["LmjF26.snoRNA.0452:snoRNA"]},"lmjf03.0780:pep":{"exact":[["LmjF03.0780:pep",0,"LmjF.03.0780","LmjF.03",293545,302884]],"prefix":[]},"lmjf27.snorna.0150:":{"exact":[],"prefix":["LmjF27.snoRNA.0150:snoRNA"]},"lmjf26.0230":{"exact":[["LmjF26.0230",0,"LmjF.26.0230","LmjF.26",59666,60797]],"prefix":["LmjF26.0230:mRNA","LmjF26.0230:pep"]},"lmjf28.1800":{"exact":[["LmjF28.1800",0,"LmjF.28.1800","LmjF.28",692345,700052]],"prefix":["LmjF28.1800:mRNA","LmjF28.1800:pep"]},"lmjf35.2600:pe":{"exact":[],"prefix":["LmjF35.2600:pep"]},"lmjf12.116":{"exact":[],"prefix":["LmjF12.1160","LmjF12.1160:pep","LmjF12.1160:mRNA"]},"lmjf18.0450:mrna":{"exact":[["LmjF18.0450:mRNA",0,"LmjF.18.0450","LmjF.18",192733,194122]],"prefix":[]},"lmjf04.1040:pe":{"exact":[],"prefix":["LmjF04.1040:pep"]},"68126770":{"exact":[["68126770",0,"LmjF.24.1870","LmjF.24",690210,694095]],"prefix":[]},"chr36_tmp.159":{"exact":[],"prefix":["CHR36_tmp.159c"]},"lmjf.30.0690":{"exact":[["LmjF.30.0690",0,"LmjF.30.0690","LmjF.30",223269,223470]],"prefix":[]},"lmjf22.snorna.0013:sn":{"exact":[],"prefix":["LmjF22.snoRNA.0013:snoRNA"]},"serine peptida":{"exact":[],"prefix":["serine peptidase","serine peptidase family S51","Serine peptidase","serine peptidase clan SF","serine peptidase clan SC"]}}