{"15787121":{"exact":[],"prefix":["157871211","157871213","157871215","157871217","157871219"]},"lmjf.09.t141":{"exact":[],"prefix":["LmjF.09.T1410"]},"lmjf.15.038":{"exact":[],"prefix":["LmjF.15.0380"]},"lmjf.21.t059":{"exact":[],"prefix":["LmjF.21.T0590"]},"lmjf26.snorna.0088:sno":{"exact":[],"prefix":["LmjF26.snoRNA.0088:snoRNA"]},"lmjf.07.t117":{"exact":[],"prefix":["LmjF.07.T1170","LmjF.07.T1175","LmjF.07.T1177"]},"lmjf36.5090:m":{"exact":[],"prefix":["LmjF36.5090:mRNA"]},"chr08_tmp.029":{"exact":[],"prefix":["CHR08_tmp.0290"]},"lmjf36.2990:pe":{"exact":[],"prefix":["LmjF36.2990:pep"]},"lmjf30.1130:mr":{"exact":[],"prefix":["LmjF30.1130:mRNA"]},"lmjf.16.0910:pseudogeni":{"exact":[],"prefix":["LmjF.16.0910:pseudogenic.transcript","LmjF.16.0910:pseudogenic.transcript:pep"]},"lmjf12.1320:mr":{"exact":[],"prefix":["LmjF12.1320:mRNA"]},"lmjf.14.0665:pseudogenic.transcr":{"exact":[],"prefix":["LmjF.14.0665:pseudogenic.transcript","LmjF.14.0665:pseudogenic.transcript:pep"]},"lmjf26.1080:mr":{"exact":[],"prefix":["LmjF26.1080:mRNA"]},"chr22_tmp.1250":{"exact":[["CHR22_tmp.1250",0,"LmjF.22.1350","LmjF.22",567912,569100]],"prefix":[]},"lmjf16.017":{"exact":[],"prefix":["LmjF16.0170","LmjF16.0170:pep","LmjF16.0170:mRNA"]},"lmjf.31.1460":{"exact":[["LmjF.31.1460",0,"LmjF.31.1460","LmjF.31",686913,687825]],"prefix":[]},"lmjf.36.5120":{"exact":[["LmjF.36.5120",0,"LmjF.36.5120","LmjF.36",1974434,1975175]],"prefix":[]},"lmjf20.0320:mrn":{"exact":[],"prefix":["LmjF20.0320:mRNA"]},"lmjf27.1710:pseudogenic_tran":{"exact":[],"prefix":["LmjF27.1710:pseudogenic_transcript","LmjF27.1710:pseudogenic_transcript:pep"]},"lmjf33.1550":{"exact":[["LmjF33.1550",0,"LmjF.33.1550","LmjF.33",741190,742174]],"prefix":["LmjF33.1550:pep","LmjF33.1550:mRNA"]},"chr34_tmp.2770":{"exact":[["CHR34_tmp.2770",0,"LmjF.34.3190","LmjF.34",1413909,1415442]],"prefix":[]},"lmjf20.1175:pseudogenic_transc":{"exact":[],"prefix":["LmjF20.1175:pseudogenic_transcript","LmjF20.1175:pseudogenic_transcript:pep"]},"lmjf.31.125":{"exact":[],"prefix":["LmjF.31.1250"]},"lmjf08.1170":{"exact":[["LmjF08.1170",0,"LmjF.08.1170","LmjF.08",519803,521132]],"prefix":["LmjF08.1170:pep","LmjF08.1170:mRNA"]},"lmjf.34.trnathr":{"exact":[],"prefix":["LmjF.34.TRNATHR.01"]},"lmjf09.001":{"exact":[],"prefix":["LmjF09.0010","LmjF09.0010:pep","LmjF09.0010:mRNA"]},"lmjf36.3780:":{"exact":[],"prefix":["LmjF36.3780:mRNA","LmjF36.3780:pep"]},"lmjf05.0690:mrna":{"exact":[["LmjF05.0690:mRNA",0,"LmjF.05.0690","LmjF.05",238659,246723]],"prefix":[]},"lmjf.30.t01":{"exact":[],"prefix":["LmjF.30.T0100","LmjF.30.T0110","LmjF.30.T0120","LmjF.30.T0130","LmjF.30.T0140","LmjF.30.T0150","LmjF.30.T0152","LmjF.30.T0170","LmjF.30.T0175","LmjF.30.T0180","LmjF.30.T0190"]},"kmpii-1":{"exact":[["KMPII-1",0,"LmjF.35.2210","LmjF.35",902824,903103]],"prefix":[]},"lmjf.36.6785:":{"exact":[],"prefix":["LmjF.36.6785:pseudogenic.transcript","LmjF.36.6785:pseudogenic.transcript:pep"]}}