{"lm33cs1c1.5":{"exact":[["LM33Cs1C1.5",0,"LmjF.33.snoRNA0125","LmjF.33",102650,102745]],"prefix":[]},"lmjf28.0230:pe":{"exact":[],"prefix":["LmjF28.0230:pep"]},"lmjf.20.153":{"exact":[],"prefix":["LmjF.20.1530"]},"lmjf.36.t559":{"exact":[],"prefix":["LmjF.36.T5590","LmjF.36.T5595"]},"lmjf30.0540:mrn":{"exact":[],"prefix":["LmjF30.0540:mRNA"]},"lmjf21.0620:mrna":{"exact":[["LmjF21.0620:mRNA",0,"LmjF.21.0620","LmjF.21",191441,193802]],"prefix":[]},"lmjf18.077":{"exact":[],"prefix":["LmjF18.0770","LmjF18.0770:pep","LmjF18.0770:mRNA"]},"lmjf24.1050":{"exact":[["LmjF24.1050",0,"LmjF.24.1050","LmjF.24",363699,367524]],"prefix":["LmjF24.1050:pep","LmjF24.1050:mRNA"]},"lmjf17.1450:mr":{"exact":[],"prefix":["LmjF17.1450:mRNA"]},"lmjf26.2210:mr":{"exact":[],"prefix":["LmjF26.2210:mRNA"]},"lmjf.26.1160":{"exact":[["LmjF.26.1160",0,"LmjF.26.1160","LmjF.26",379600,382534]],"prefix":[]},"lmjf.33.t2800":{"exact":[["LmjF.33.T2800",1,"LmjF.33.T2800","LmjF.33",1273298,1274702]],"prefix":[]},"lmjf.20.snorna0265":{"exact":[["LmjF.20.snoRNA0265",0,"LmjF.20.snoRNA0265","LmjF.20",338185,338263]],"prefix":[]},"1460899":{"exact":[],"prefix":["146089914","146089918","146089910"]},"lmjf36.snorna.0084":{"exact":[["LmjF36.snoRNA.0084",0,"LmjF.36.snoRNA0084","LmjF.36",942322,942414]],"prefix":["LmjF36.snoRNA.0084:snoRNA"]},"lmjf26.087":{"exact":[],"prefix":["LmjF26.0870:pep","LmjF26.0870:mRNA","LmjF26.0870"]},"l8325.1":{"exact":[],"prefix":["L8325.13","L8325.12","L8325.10"]},"lmjf26.snorna.0510:snor":{"exact":[],"prefix":["LmjF26.snoRNA.0510:snoRNA"]},"lmjf.35.t0960":{"exact":[["LmjF.35.T0960",1,"LmjF.35.T0960","LmjF.35",430105,433173]],"prefix":[]},"68129041":{"exact":[["68129041",0,"LmjF.33.2070","LmjF.33",927968,930998]],"prefix":[]}," cla":{"exact":[],"prefix":[" Clan SJ"," Clan SF"," Clan CA"," clan SC"," Clan MA(M)"," Clan MF"," Clan MA(E)"," Clan ME"," clan SB"," Clan CD"," Clan SC"," Clan MG"," Clan M-"," Clan SP"," clan AD"," Clan MH"," Clan MK"," Clan MC"," Clan MP"]},"lmjf33.261":{"exact":[],"prefix":["LmjF33.2610","LmjF33.2610:pep","LmjF33.2610:mRNA"]},"lmjf35.1640:mr":{"exact":[],"prefix":["LmjF35.1640:mRNA"]},"lmjf07.061":{"exact":[],"prefix":["LmjF07.0610","LmjF07.0610:pep","LmjF07.0610:mRNA","LmjF07.0615","LmjF07.0615:pep","LmjF07.0615:mRNA"]},"lmjf26.snorna.0019:":{"exact":[],"prefix":["LmjF26.snoRNA.0019:snoRNA"]},"lmjf.25.t061":{"exact":[],"prefix":["LmjF.25.T0610","LmjF.25.T0612"]},"lmjf35.5320:mr":{"exact":[],"prefix":["LmjF35.5320:mRNA"]},"chr22_tmp.131":{"exact":[],"prefix":["CHR22_tmp.1310"]}}