{"lmjf34.0600:pep":{"exact":[["LmjF34.0600:pep",0,"LmjF.34.0600","LmjF.34",252654,255216]],"prefix":[]},"lmjf.24.t041":{"exact":[],"prefix":["LmjF.24.T0410"]},"lmjf.27.1140":{"exact":[["LmjF.27.1140",0,"LmjF.27.1140","LmjF.27",483083,484835]],"prefix":[]},"6812809":{"exact":[],"prefix":["68128090","68128091","68128092","68128093","68128094","68128095","68128096","68128097","68128098","68128099"]},"157875406":{"exact":[["157875406",0,"LmjF.34.0070","LmjF.34",22864,23776]],"prefix":[]},"lmjf36.5390:":{"exact":[],"prefix":["LmjF36.5390:mRNA","LmjF36.5390:pep"]},"lmjf27.snorna.0018:snorn":{"exact":[],"prefix":["LmjF27.snoRNA.0018:snoRNA"]},"lmjf09.0340:pep":{"exact":[["LmjF09.0340:pep",0,"LmjF.09.0340","LmjF.09",135590,138785]],"prefix":[]},"lmjf30.3170:p":{"exact":[],"prefix":["LmjF30.3170:pep"]},"lmjf17.041":{"exact":[],"prefix":["LmjF17.0410:mRNA","LmjF17.0410:pep","LmjF17.0410"]},"lm24.168":{"exact":[["LM24.168",0,"LmjF.24.1680","LmjF.24",634099,635440]],"prefix":[]},"lmjf36.2845":{"exact":[["LmjF36.2845",0,"LmjF.36.2845","LmjF.36",1166589,1166868]],"prefix":["LmjF36.2845:pep","LmjF36.2845:mRNA"]},"13407332":{"exact":[],"prefix":["134073325","134073324"]},"lmjf.33.t1630":{"exact":[["LmjF.33.T1630",1,"LmjF.33.T1630","LmjF.33",771372,772195]],"prefix":[]},"lmjf.35.088":{"exact":[],"prefix":["LmjF.35.0880"]},"lmjf28.2530:pep":{"exact":[["LmjF28.2530:pep",0,"LmjF.28.2530","LmjF.28",979045,981856]],"prefix":[]},"lmjf26.snorna.0469:snorna":{"exact":[["LmjF26.snoRNA.0469:snoRNA",0,"LmjF.26.snoRNA0469","LmjF.26",673564,673645]],"prefix":[]},"lmjf16.0400:mrna":{"exact":[["LmjF16.0400:mRNA",0,"LmjF.16.0400","LmjF.16",141074,142145]],"prefix":[]},"lmjf04.1010:pep":{"exact":[["LmjF04.1010:pep",0,"LmjF.04.1010","LmjF.04",390500,391169]],"prefix":[]},"lmjf.29.t0710":{"exact":[["LmjF.29.T0710",1,"LmjF.29.T0710","LmjF.29",259210,262409]],"prefix":[]},"lmjf.30.173":{"exact":[],"prefix":["LmjF.30.1730"]},"389594419":{"exact":[["389594419",0,"LmjF.35.0350","LmjF.35",94487,96599]],"prefix":[]},"lmjf.35.t3750":{"exact":[["LmjF.35.T3750",1,"LmjF.35.T3750","LmjF.35",1509859,1513222]],"prefix":[]},"lmjf.27.t0450":{"exact":[["LmjF.27.T0450",1,"LmjF.27.T0450","LmjF.27",126398,128011]],"prefix":[]},"1237":{"exact":[],"prefix":["1237122"]},"lmjf33.1260:pe":{"exact":[],"prefix":["LmjF33.1260:pep"]},"lmjf.11.0570:pseudogenic.transcript:":{"exact":[],"prefix":["LmjF.11.0570:pseudogenic.transcript:pep"]},"lmjf21.0791.1:pe":{"exact":[],"prefix":["LmjF21.0791.1:pep"]},"321438318":{"exact":[["321438318",0,"LmjF.27.0100","LmjF.27",25525,27508]],"prefix":[]},"lmjf.35.t3235-sno":{"exact":[],"prefix":["LmjF.35.T3235-snoRNAs"]},"lmjf25.2020:p":{"exact":[],"prefix":["LmjF25.2020:pep"]},"lmjf15.0940:pep":{"exact":[["LmjF15.0940:pep",0,"LmjF.15.0940","LmjF.15",424398,427992]],"prefix":[]},"lmjf.25.snorna0139":{"exact":[["LmjF.25.snoRNA0139",0,"LmjF.25.snoRNA0139","LmjF.25",617589,617680]],"prefix":[]},"lmjf27.snorna.0004:snor":{"exact":[],"prefix":["LmjF27.snoRNA.0004:snoRNA"]},"lmjf.36.t664":{"exact":[],"prefix":["LmjF.36.T6640","LmjF.36.T6645"]},"lmjf36.2780:pe":{"exact":[],"prefix":["LmjF36.2780:pep"]},"lmjf25.1070":{"exact":[["LmjF25.1070",0,"LmjF.25.1070","LmjF.25",415311,417888]],"prefix":["LmjF25.1070:mRNA","LmjF25.1070:pep"]},"lmjf26.snorna.0435:snorna":{"exact":[["LmjF26.snoRNA.0435:snoRNA",0,"LmjF.26.snoRNA0435","LmjF.26",736778,736865]],"prefix":[]},"lmjf26.snorna.0069:sno":{"exact":[],"prefix":["LmjF26.snoRNA.0069:snoRNA"]},"lmjf08.057":{"exact":[],"prefix":["LmjF08.0570","LmjF08.0570:pep","LmjF08.0570:mRNA"]},"lmjf11.1070:pe":{"exact":[],"prefix":["LmjF11.1070:pep"]},"157873685":{"exact":[["157873685",0,"LmjF.32.0340","LmjF.32",123869,125744]],"prefix":[]},"lmjf34.4040:mrn":{"exact":[],"prefix":["LmjF34.4040:mRNA"]}}