{"lmjf27.2450:pep":{"exact":[["LmjF27.2450:pep",0,"LmjF.27.2450","LmjF.27",1084948,1086292]],"prefix":[]},"lmjf26.snorna.0040:s":{"exact":[],"prefix":["LmjF26.snoRNA.0040:snoRNA"]},"lmjf36.5270:mrn":{"exact":[],"prefix":["LmjF36.5270:mRNA"]},"lmjf12.1050:":{"exact":[],"prefix":["LmjF12.1050:pep","LmjF12.1050:mRNA"]},"lmjf02.0610:mrna":{"exact":[["LmjF02.0610:mRNA",0,"LmjF.02.0610","LmjF.02",315239,316205]],"prefix":[]},"lmjf27.snorna.0048:snorna":{"exact":[["LmjF27.snoRNA.0048:snoRNA",0,"LmjF.27.snoRNA0169","LmjF.27",381085,381154]],"prefix":[]},"bifunctional aminoacyl-t":{"exact":[],"prefix":["bifunctional aminoacyl-tRNA synthetase"]},"lmjf31.0450:mr":{"exact":[],"prefix":["LmjF31.0450:mRNA"]},"lmjf34.4600:":{"exact":[],"prefix":["LmjF34.4600:pep","LmjF34.4600:mRNA"]},"lmjf35.5280:pep":{"exact":[["LmjF35.5280:pep",0,"LmjF.35.5280","LmjF.35",2043411,2044179]],"prefix":[]},"lmjf35.197":{"exact":[],"prefix":["LmjF35.1970:mRNA","LmjF35.1970","LmjF35.1970:pep"]},"lmjf14.1390:p":{"exact":[],"prefix":["LmjF14.1390:pep"]},"lmjf.33.043":{"exact":[],"prefix":["LmjF.33.0430"]},"lmjf.18.0820":{"exact":[["LmjF.18.0820",0,"LmjF.18.0820","LmjF.18",335590,343564]],"prefix":[]},"lmjf.36.3780":{"exact":[["LmjF.36.3780",0,"LmjF.36.3780","LmjF.36",1446159,1447110]],"prefix":[]},"15787502":{"exact":[],"prefix":["157875021","157875023","157875026","157875028"]},"157873981":{"exact":[["157873981",0,"LmjF.32.1690","LmjF.32",660277,661969]],"prefix":[]},"lmjf36.1630:":{"exact":[],"prefix":["LmjF36.1630:pep","LmjF36.1630:mRNA"]},"lmjf.32.t142":{"exact":[],"prefix":["LmjF.32.T1420"]},"lmjf13.0640:mr":{"exact":[],"prefix":["LmjF13.0640:mRNA"]},"lmjf09.1500:pseudogenic_transcript:pe":{"exact":[],"prefix":["LmjF09.1500:pseudogenic_transcript:pep"]},"lmjf20.snorna.0217:snorn":{"exact":[],"prefix":["LmjF20.snoRNA.0217:snoRNA"]},"lmjf.27.rrna.07":{"exact":[["LmjF.27.rRNA.07",0,"LmjF.27.rRNA.07","LmjF.27",995699,995982]],"prefix":[]},"22.t00":{"exact":[],"prefix":["22.t00172","22.t00171"]},"lmjf.16.1210":{"exact":[["LmjF.16.1210",0,"LmjF.16.1210","LmjF.16",477247,480955]],"prefix":[]},"lmjf.16.t1005":{"exact":[["LmjF.16.T1005",1,"LmjF.16.T1005","LmjF.16",374293,378091]],"prefix":[]},"lmjf27.snorna.0014:snorna":{"exact":[["LmjF27.snoRNA.0014:snoRNA",0,"LmjF.27.snoRNA0161","LmjF.27",375938,376007]],"prefix":[]},"lmjf29.2240:mrna":{"exact":[["LmjF29.2240:mRNA",0,"LmjF.29.2240","LmjF.29",987763,990370]],"prefix":[]},"lmjf20.1010:p":{"exact":[],"prefix":["LmjF20.1010:pep"]},"lmjf32.0910:pe":{"exact":[],"prefix":["LmjF32.0910:pep"]},"lm5.92":{"exact":[["LM5.92",0,"LmjF.05.0920","LmjF.05",338704,342049]],"prefix":[]},"lmjf08.1180:mrn":{"exact":[],"prefix":["LmjF08.1180:mRNA"]},"lmjf14.1320":{"exact":[["LmjF14.1320",0,"LmjF.14.1320","LmjF.14",554287,555685]],"prefix":["LmjF14.1320:pep","LmjF14.1320:mRNA"]},"lmjf35.0140:p":{"exact":[],"prefix":["LmjF35.0140:pep"]},"lmjf19.0880:p":{"exact":[],"prefix":["LmjF19.0880:pep"]},"157874164":{"exact":[["157874164",0,"LmjF.32.2500","LmjF.32",977842,978331]],"prefix":[]},"lmjf36.1430:pep":{"exact":[["LmjF36.1430:pep",0,"LmjF.36.1430","LmjF.36",526908,527544]],"prefix":[]},"lmjf06.0220:pep":{"exact":[["LmjF06.0220:pep",0,"LmjF.06.0220","LmjF.06",73564,74428]],"prefix":[]},"lmjf34.0470:p":{"exact":[],"prefix":["LmjF34.0470:pep"]},"lmjf18.1380:pe":{"exact":[],"prefix":["LmjF18.1380:pep"]},"lmjf21.1520:p":{"exact":[],"prefix":["LmjF21.1520:pep"]},"lmjf36.6400:m":{"exact":[],"prefix":["LmjF36.6400:mRNA"]},"lmjf.29.t1272":{"exact":[["LmjF.29.T1272",1,"LmjF.29.T1272","LmjF.29",513870,514096]],"prefix":[]},"lmjf24.1500:":{"exact":[],"prefix":["LmjF24.1500:mRNA","LmjF24.1500:pep"]}}