{"lmjf30.1450:":{"exact":[],"prefix":["LmjF30.1450:pep","LmjF30.1450:mRNA"]},"lmjf14.1440":{"exact":[["LmjF14.1440",0,"LmjF.14.1440","LmjF.14",605549,608342]],"prefix":["LmjF14.1440:pep","LmjF14.1440:mRNA"]},"lmjf35.3040:mrn":{"exact":[],"prefix":["LmjF35.3040:mRNA"]},"lmjf19.0560:mrn":{"exact":[],"prefix":["LmjF19.0560:mRNA"]},"lmjf.32.t0980":{"exact":[["LmjF.32.T0980",1,"LmjF.32.T0980","LmjF.32",376253,386999]],"prefix":[]},"lmjf.20.t007":{"exact":[],"prefix":["LmjF.20.T0070"]},"lmjf15.0285:mrn":{"exact":[],"prefix":["LmjF15.0285:mRNA"]},"lmjf.05.066":{"exact":[],"prefix":["LmjF.05.0660"]},"lmjf24.0020:mrn":{"exact":[],"prefix":["LmjF24.0020:mRNA"]},"lmjf.16.1570":{"exact":[["LmjF.16.1570",0,"LmjF.16.1570","LmjF.16",665077,666103]],"prefix":[]},"lmjf27.1140:mr":{"exact":[],"prefix":["LmjF27.1140:mRNA"]},"lmjf14.1230:":{"exact":[],"prefix":["LmjF14.1230:pep","LmjF14.1230:mRNA"]},"lmjf22.154":{"exact":[],"prefix":["LmjF22.1540","LmjF22.1540:pep","LmjF22.1540:mRNA"]},"lmjf.24.080":{"exact":[],"prefix":["LmjF.24.0800"]},"15786804":{"exact":[],"prefix":["157868041","157868043","157868045","157868047"]},"lmjf13.0910:mrna":{"exact":[["LmjF13.0910:mRNA",0,"LmjF.13.0910","LmjF.13",310581,313077]],"prefix":[]},"lmjf35.1970:mrn":{"exact":[],"prefix":["LmjF35.1970:mRNA"]},"lmjf.36.46":{"exact":[],"prefix":["LmjF.36.4600","LmjF.36.4610","LmjF.36.4620","LmjF.36.4630","LmjF.36.4640","LmjF.36.4650","LmjF.36.4660","LmjF.36.4670","LmjF.36.4675","LmjF.36.4680","LmjF.36.4690"]},"157872487":{"exact":[["157872487",0,"LmjF.30.1850","LmjF.30",688914,693039]],"prefix":[]},"lmjf35.1000:mrna":{"exact":[["LmjF35.1000:mRNA",0,"LmjF.35.1000","LmjF.35",445599,446574]],"prefix":[]},"lmjf36.1980:pep":{"exact":[["LmjF36.1980:pep",0,"LmjF.36.1980","LmjF.36",782392,783616]],"prefix":[]},"lmjf29.1370:mrn":{"exact":[],"prefix":["LmjF29.1370:mRNA"]},"lmjf09.0770:":{"exact":[],"prefix":["LmjF09.0770:pep","LmjF09.0770:mRNA"]},"abch2":{"exact":[["ABCH2",0,"LmjF.29.1640","LmjF.29",757787,759182]],"prefix":[]},"chr16_tmp.012":{"exact":[],"prefix":["CHR16_tmp.0120"]},"lmjf.05.snorna0063":{"exact":[["LmjF.05.snoRNA0063",0,"LmjF.05.snoRNA0063","LmjF.05",448952,449045]],"prefix":[]},"lmjf26.snorna.0532:snorna":{"exact":[["LmjF26.snoRNA.0532:snoRNA",0,"LmjF.26.snoRNA0532","LmjF.26",651339,651405]],"prefix":[]},"lmjf18.0720:pe":{"exact":[],"prefix":["LmjF18.0720:pep"]},"lmjf34.2510:mr":{"exact":[],"prefix":["LmjF34.2510:mRNA"]},"lmjf.31.266":{"exact":[],"prefix":["LmjF.31.2660","LmjF.31.2660:pseudogenic.transcript:pep","LmjF.31.2660:pseudogenic.transcript"]},"lmjf32.249":{"exact":[],"prefix":["LmjF32.2490:pep","LmjF32.2490:mRNA","LmjF32.2490"]},"15787262":{"exact":[],"prefix":["157872621","157872623","157872625","157872627","157872629"]},"lmjf26.2680:p":{"exact":[],"prefix":["LmjF26.2680:pep"]},"68224059":{"exact":[["68224059",0,"LmjF.22.0230","LmjF.22",101893,103351]],"prefix":[]},"lmjf06.049":{"exact":[],"prefix":["LmjF06.0490","LmjF06.0490:pep","LmjF06.0490:mRNA"]},"lmjf08.0010:mrna":{"exact":[["LmjF08.0010:mRNA",0,"LmjF.08.0010","LmjF.08",4055,7652]],"prefix":[]},"lmjf06.1100:":{"exact":[],"prefix":["LmjF06.1100:pep","LmjF06.1100:mRNA"]}}