{"lmjf14.1040:m":{"exact":[],"prefix":["LmjF14.1040:mRNA"]},"lmjf27.113":{"exact":[],"prefix":["LmjF27.1130","LmjF27.1130:pep","LmjF27.1130:mRNA"]},"lmjf35.2650:pep":{"exact":[["LmjF35.2650:pep",0,"LmjF.35.2650","LmjF.35",1081442,1082246]],"prefix":[]},"lmjf36.5250:mrna":{"exact":[["LmjF36.5250:mRNA",0,"LmjF.36.5250","LmjF.36",2021222,2032064]],"prefix":[]},"157871836":{"exact":[["157871836",0,"LmjF.28.1850","LmjF.28",714641,716993]],"prefix":[]},"lmjf03.0280":{"exact":[["LmjF03.0280",0,"LmjF.03.0280","LmjF.03",74028,76956]],"prefix":["LmjF03.0280:pep","LmjF03.0280:mRNA"]},"lmjf3.019":{"exact":[],"prefix":["LmjF3.0190"]},"lmjf36.4730:mr":{"exact":[],"prefix":["LmjF36.4730:mRNA"]},"lmjf29.0560:pep":{"exact":[["LmjF29.0560:pep",0,"LmjF.29.0560","LmjF.29",208587,209805]],"prefix":[]},"1578655":{"exact":[],"prefix":["157865501","157865503","157865505","157865507","157865509","157865511","157865513","157865515","157865517","157865519","157865521","157865524","157865526","157865528","157865530","157865532","157865534","157865536","157865538","157865540",{"name":"too many matches","hitLimit":1}]},"lmjf17.0710":{"exact":[["LmjF17.0710",0,"LmjF.17.0710","LmjF.17",376452,378885]],"prefix":["LmjF17.0710:pep","LmjF17.0710:mRNA"]},"lmjf.34.221":{"exact":[],"prefix":["LmjF.34.2210"]},"lmjf.25.t18":{"exact":[],"prefix":["LmjF.25.T1800","LmjF.25.T1810","LmjF.25.T1820","LmjF.25.T1826","LmjF.25.T1830","LmjF.25.T1840","LmjF.25.T1850","LmjF.25.T1860","LmjF.25.T1870","LmjF.25.T1875","LmjF.25.T1880","LmjF.25.T1890"]},"lmjf.27.2590:pseudogenic.transcript:pep":{"exact":[["LmjF.27.2590:pseudogenic.transcript:pep",0,"LmjF.27.2590","LmjF.27",1097432,1110332]],"prefix":[]},"chr34_tmp.148":{"exact":[],"prefix":["CHR34_tmp.1480"]},"lmjf.28.t258":{"exact":[],"prefix":["LmjF.28.T2580"]},"lmjf01.0110:m":{"exact":[],"prefix":["LmjF01.0110:mRNA"]},"lmjf15.1570:m":{"exact":[],"prefix":["LmjF15.1570:mRNA"]},"lmjf.27.t113":{"exact":[],"prefix":["LmjF.27.T1130"]},"323363820":{"exact":[["323363820",0,"LmjF.35.2000","LmjF.35",803755,806500]],"prefix":[]},"68223900":{"exact":[["68223900",0,"LmjF.21.0820","LmjF.21",272181,276303]],"prefix":[]},"lmjf09.1430:pe":{"exact":[],"prefix":["LmjF09.1430:pep"]},"lmjf.35.t0385":{"exact":[["LmjF.35.T0385",1,"LmjF.35.T0385","LmjF.35",110077,116367]],"prefix":[]},"lmjf.02.slrna.0540":{"exact":[["LmjF.02.SLRNA.0540",0,"LmjF.02.SLRNA.0540","LmjF.02",293833,294288]],"prefix":[]},"lmjf36.0250:mr":{"exact":[],"prefix":["LmjF36.0250:mRNA"]},"lmjf24.1630:pep":{"exact":[["LmjF24.1630:pep",0,"LmjF.24.1630","LmjF.24",614838,616662]],"prefix":[]},"lmjf.15.0620":{"exact":[["LmjF.15.0620",0,"LmjF.15.0620","LmjF.15",260637,261984]],"prefix":[]},"chr18_tmp.042":{"exact":[],"prefix":["CHR18_tmp.0420"]},"lmjf26.snorna.0184:s":{"exact":[],"prefix":["LmjF26.snoRNA.0184:snoRNA"]},"lmjf28.0825:p":{"exact":[],"prefix":["LmjF28.0825:pep"]},"lmjf35.0290:m":{"exact":[],"prefix":["LmjF35.0290:mRNA"]},"lmjf24.0940:":{"exact":[],"prefix":["LmjF24.0940:mRNA","LmjF24.0940:pep"]},"lmjf14.0040:mr":{"exact":[],"prefix":["LmjF14.0040:mRNA"]},"lmjf17.0790:mrna":{"exact":[["LmjF17.0790:mRNA",0,"LmjF.17.0790","LmjF.17",345257,347366]],"prefix":[]},"68127462":{"exact":[["68127462",0,"LmjF.28.1110","LmjF.28",412688,414578]],"prefix":[]},"lmjf20.snorna.0067:snor":{"exact":[],"prefix":["LmjF20.snoRNA.0067:snoRNA"]},"lmjf.25.t1515":{"exact":[["LmjF.25.T1515",1,"LmjF.25.T1515","LmjF.25",605153,606349]],"prefix":[]},"lmjf10.trna":{"exact":[],"prefix":["LmjF10.TRNALYS.01","LmjF10.TRNALYS.01:tRNA","LmjF10.TRNAGLY.01","LmjF10.TRNAGLY.01:tRNA","LmjF10.TRNAASN.01","LmjF10.TRNAASN.01:tRNA"]},"chr08_tmp.0110":{"exact":[["CHR08_tmp.0110",0,"LmjF.08.0110","LmjF.08",32351,34283]],"prefix":[]},"lmjf19.1370:pep":{"exact":[["LmjF19.1370:pep",0,"LmjF.19.1370","LmjF.19",608806,611029]],"prefix":[]},"lmjf.29.t145":{"exact":[],"prefix":["LmjF.29.T1450"]},"lmjf.32.0473":{"exact":[["LmjF.32.0473",0,"LmjF.32.0473","LmjF.32",178502,179123]],"prefix":[]},"lmjf28.218":{"exact":[],"prefix":["LmjF28.2180:mRNA","LmjF28.2180","LmjF28.2180:pep"]},"lmjf27.1720:pseudogenic_":{"exact":[],"prefix":["LmjF27.1720:pseudogenic_transcript","LmjF27.1720:pseudogenic_transcript:pep"]},"68125309":{"exact":[["68125309",0,"LmjF.14.0960","LmjF.14",392810,396158]],"prefix":[]},"lmjf.27.trrna.3":{"exact":[],"prefix":["LmjF.27.TrRNA.37-rRNA.43","LmjF.27.TrRNA.38-rRNA.45-rRNA.46","LmjF.27.TrRNA.39","LmjF.27.TrRNA.30","LmjF.27.TrRNA.36"]}}