{"lmjf.29.1250":{"exact":[["LmjF.29.1250",0,"LmjF.29.1250","LmjF.29",494972,500429]],"prefix":[]},"lmjf34.0140:mr":{"exact":[],"prefix":["LmjF34.0140:mRNA"]},"lmjf16.0350:mr":{"exact":[],"prefix":["LmjF16.0350:mRNA"]},"lmjf.33.snorna008":{"exact":[],"prefix":["LmjF.33.snoRNA0089"]},"lmjf16.0030:pep":{"exact":[["LmjF16.0030:pep",0,"LmjF.16.0030","LmjF.16",5528,6626]],"prefix":[]},"68125997":{"exact":[["68125997",0,"LmjF.18.1340","LmjF.18",573572,575879]],"prefix":[]},"lmjf.20.128":{"exact":[],"prefix":["LmjF.20.1280"]},"lmjf28.0580:mrn":{"exact":[],"prefix":["LmjF28.0580:mRNA"]},"lmjf36.4130:p":{"exact":[],"prefix":["LmjF36.4130:pep"]},"lmjf.04.035":{"exact":[],"prefix":["LmjF.04.0350","LmjF.04.0350:pseudogenic.transcript","LmjF.04.0350:pseudogenic.transcript:pep"]},"lmjf29.1530:pe":{"exact":[],"prefix":["LmjF29.1530:pep"]},"lmjf25.0950":{"exact":[["LmjF25.0950",0,"LmjF.25.0950","LmjF.25",357416,358901]],"prefix":["LmjF25.0950:mRNA","LmjF25.0950:pep"]},"lmjf.36.t522":{"exact":[],"prefix":["LmjF.36.T5220"]},"lmjf17.1000:":{"exact":[],"prefix":["LmjF17.1000:mRNA","LmjF17.1000:pep"]},"lmjf21.1550:":{"exact":[],"prefix":["LmjF21.1550:mRNA","LmjF21.1550:pep"]},"lmjf34.4420:mr":{"exact":[],"prefix":["LmjF34.4420:mRNA"]},"321399860":{"exact":[["321399860",0,"LmjF.33.1050","LmjF.33",492355,493642]],"prefix":[]},"lmjf.14.1355:pseudogenic.transcript:":{"exact":[],"prefix":["LmjF.14.1355:pseudogenic.transcript:pep"]},"lmjf18.1390:mrn":{"exact":[],"prefix":["LmjF18.1390:mRNA"]},"lmjf18.0670:":{"exact":[],"prefix":["LmjF18.0670:mRNA","LmjF18.0670:pep"]},"lmjf23.107":{"exact":[],"prefix":["LmjF23.1070:pep","LmjF23.1070:mRNA","LmjF23.1070","LmjF23.1075:mRNA","LmjF23.1075","LmjF23.1075:pep"]},"lmjf.26.15":{"exact":[],"prefix":["LmjF.26.1500","LmjF.26.1510","LmjF.26.1520","LmjF.26.1530","LmjF.26.1540","LmjF.26.1550","LmjF.26.1560","LmjF.26.1570","LmjF.26.1580","LmjF.26.1590"]},"lmjf36.4980":{"exact":[["LmjF36.4980",0,"LmjF.36.4980","LmjF.36",1932837,1933842]],"prefix":["LmjF36.4980:pep","LmjF36.4980:mRNA"]},"lmjf34.2140:m":{"exact":[],"prefix":["LmjF34.2140:mRNA"]}," family c4":{"exact":[],"prefix":[" family C48"]},"157864657":{"exact":[["157864657",0,"LmjF.08.0080","LmjF.08",20992,23050]],"prefix":[]},"lmjf.30.235":{"exact":[],"prefix":["LmjF.30.2350"]},"lmjf35.2470:m":{"exact":[],"prefix":["LmjF35.2470:mRNA"]},"lmjf26.1620:pep":{"exact":[["LmjF26.1620:pep",0,"LmjF.26.1620","LmjF.26",596990,598286]],"prefix":[]},"lmjf.27.0860":{"exact":[["LmjF.27.0860",0,"LmjF.27.0860","LmjF.27",344409,347523]],"prefix":[]},"lmjf.13.t1505":{"exact":[["LmjF.13.T1505",1,"LmjF.13.T1505","LmjF.13",550371,553238]],"prefix":[]},"lmjf33.1660:":{"exact":[],"prefix":["LmjF33.1660:pep","LmjF33.1660:mRNA"]}}