{"68124172":{"exact":[["68124172",0,"LmjF.06.1080","LmjF.06",448193,448868]],"prefix":[]},"lmjf36.2980":{"exact":[["LmjF36.2980",0,"LmjF.36.2980","LmjF.36",1219489,1220191]],"prefix":["LmjF36.2980:pep","LmjF36.2980:mRNA"]},"lmjf18.1620":{"exact":[["LmjF18.1620",0,"LmjF.18.1620","LmjF.18",719269,719701]],"prefix":["LmjF18.1620:mRNA","LmjF18.1620:pep"]},"lmjf18.0070:":{"exact":[],"prefix":["LmjF18.0070:mRNA","LmjF18.0070:pep"]},"lmjf34.2370:mrn":{"exact":[],"prefix":["LmjF34.2370:mRNA"]},"lmjf27.snorna.0052:snorn":{"exact":[],"prefix":["LmjF27.snoRNA.0052:snoRNA"]},"lmjf.17.t0910":{"exact":[["LmjF.17.T0910",1,"LmjF.17.T0910","LmjF.17",428023,430327]],"prefix":[]},"lmjf18.snorna.011":{"exact":[],"prefix":["LmjF18.snoRNA.0110","LmjF18.snoRNA.0110:snoRNA","LmjF18.snoRNA.0111","LmjF18.snoRNA.0111:snoRNA","LmjF18.snoRNA.0112","LmjF18.snoRNA.0112:snoRNA","LmjF18.snoRNA.0113","LmjF18.snoRNA.0113:snoRNA","LmjF18.snoRNA.0114:snoRNA","LmjF18.snoRNA.0114","LmjF18.snoRNA.0115:snoRNA","LmjF18.snoRNA.0115","LmjF18.snoRNA.0116","LmjF18.snoRNA.0116:snoRNA","LmjF18.snoRNA.0117:snoRNA","LmjF18.snoRNA.0117","LmjF18.snoRNA.0118","LmjF18.snoRNA.0118:snoRNA","LmjF18.snoRNA.0119:snoRNA","LmjF18.snoRNA.0119"]},"lmjf34.427":{"exact":[],"prefix":["LmjF34.4270","LmjF34.4270:pep","LmjF34.4270:mRNA"]},"157873740":{"exact":[["157873740",0,"LmjF.32.0590","LmjF.32",206852,207803]],"prefix":[]},"lmjf34.1820:mr":{"exact":[],"prefix":["LmjF34.1820:mRNA"]},"lmjf36.162":{"exact":[],"prefix":["LmjF36.1620:mRNA","LmjF36.1620","LmjF36.1620:pep"]},"lmjf34.2120:m":{"exact":[],"prefix":["LmjF34.2120:mRNA"]},"lmjf23.1200":{"exact":[["LmjF23.1200",0,"LmjF.23.1200","LmjF.23",564751,566221]],"prefix":["LmjF23.1200:mRNA","LmjF23.1200:pep"]},"lmjf.11.050":{"exact":[],"prefix":["LmjF.11.0500"]},"lmjf15.0500:mrn":{"exact":[],"prefix":["LmjF15.0500:mRNA"]},"lmjf26.snorna.0468:":{"exact":[],"prefix":["LmjF26.snoRNA.0468:snoRNA"]},"lm5.":{"exact":[],"prefix":["LM5.01","LM5.02","LM5.03","LM5.04","LM5.05","LM5.06","LM5.07","LM5.08","LM5.09","LM5.10","LM5.11","LM5.12","LM5.13","LM5.14","LM5.15","LM5.16","LM5.17","LM5.18","LM5.19","LM5.20",{"name":"too many matches","hitLimit":1}]},"lmjf35.2410:m":{"exact":[],"prefix":["LmjF35.2410:mRNA"]},"lmjf.05.t062":{"exact":[],"prefix":["LmjF.05.T0620"]},"lmjf.34.trnaser.01":{"exact":[["LmjF.34.TRNASER.01",0,"LmjF.34.TRNASER.01","LmjF.34",470828,470909]],"prefix":[]},"lmjf28.2970:mrn":{"exact":[],"prefix":["LmjF28.2970:mRNA"]},"lmjf.21.1330":{"exact":[["LmjF.21.1330",0,"LmjF.21.1330","LmjF.21",547308,552087]],"prefix":[]},"lmjf11.1070:mrna":{"exact":[["LmjF11.1070:mRNA",0,"LmjF.11.1070","LmjF.11",453490,454210]],"prefix":[]},"lmjf.24.t184":{"exact":[],"prefix":["LmjF.24.T1840"]},"lmjf08.0300:mr":{"exact":[],"prefix":["LmjF08.0300:mRNA"]},"lmjf29.174":{"exact":[],"prefix":["LmjF29.1740:pep","LmjF29.1740","LmjF29.1740:mRNA"]},"lmjf.20.15":{"exact":[],"prefix":["LmjF.20.1500","LmjF.20.1510","LmjF.20.1520","LmjF.20.1530","LmjF.20.1540","LmjF.20.1550","LmjF.20.1560","LmjF.20.1570","LmjF.20.1580","LmjF.20.1590"]},"lmjf24.2130:pe":{"exact":[],"prefix":["LmjF24.2130:pep"]},"lmjf28.0040:mrn":{"exact":[],"prefix":["LmjF28.0040:mRNA"]},"lmjf21.1350:":{"exact":[],"prefix":["LmjF21.1350:pep","LmjF21.1350:mRNA"]},"lmjf33.1060:":{"exact":[],"prefix":["LmjF33.1060:mRNA","LmjF33.1060:pep"]},"lmjf18.1650:mrn":{"exact":[],"prefix":["LmjF18.1650:mRNA"]},"1461007":{"exact":[],"prefix":["146100778"]},"lmjf32.2080:pe":{"exact":[],"prefix":["LmjF32.2080:pep"]},"40142906":{"exact":[],"prefix":["401429060"]},"lmjf36.4150:p":{"exact":[],"prefix":["LmjF36.4150:pep"]},"68126619":{"exact":[["68126619",0,"LmjF.24.0360","LmjF.24",110764,112567]],"prefix":[]},"lmjf36.5845:mrn":{"exact":[],"prefix":["LmjF36.5845:mRNA"]},"lmjf.23.snorna0040":{"exact":[["LmjF.23.snoRNA0040",0,"LmjF.23.snoRNA0040","LmjF.23",38239,38329]],"prefix":[]},"lmjf33.099":{"exact":[],"prefix":["LmjF33.0990","LmjF33.0990:mRNA","LmjF33.0990:pep"]},"lmjf25.1310:mrn":{"exact":[],"prefix":["LmjF25.1310:mRNA"]}}