{"lmjf.36.t295":{"exact":[],"prefix":["LmjF.36.T2950"]},"lmjf.34.t4":{"exact":[],"prefix":["LmjF.34.T4000","LmjF.34.T4010","LmjF.34.T4020","LmjF.34.T4030","LmjF.34.T4040","LmjF.34.T4050","LmjF.34.T4060","LmjF.34.T4070","LmjF.34.T4080","LmjF.34.T4090","LmjF.34.T4100","LmjF.34.T4110","LmjF.34.T4120","LmjF.34.T4130","LmjF.34.T4140","LmjF.34.T4150","LmjF.34.T4160","LmjF.34.T4170","LmjF.34.T4180","LmjF.34.T4190",{"name":"too many matches","hitLimit":1}]},"lmjf.36.4490":{"exact":[["LmjF.36.4490",0,"LmjF.36.4490","LmjF.36",1735615,1737160]],"prefix":[]},"lmjf36.456":{"exact":[],"prefix":["LmjF36.4560","LmjF36.4560:mRNA","LmjF36.4560:pep"]},"lmjf.25.0440":{"exact":[["LmjF.25.0440",0,"LmjF.25.0440","LmjF.25",140946,143058]],"prefix":[]},"lmjf.35.479":{"exact":[],"prefix":["LmjF.35.4790"]},"lmjf26.0630:mrn":{"exact":[],"prefix":["LmjF26.0630:mRNA"]},"lmjf18.snorna.0022":{"exact":[],"prefix":["LmjF18.snoRNA.0022:snoRNA"]},"lmjf18.0380:pep":{"exact":[["LmjF18.0380:pep",0,"LmjF.18.0380","LmjF.18",151794,155187]],"prefix":[]},"lmjf15.0670:m":{"exact":[],"prefix":["LmjF15.0670:mRNA"]},"lmjf16.1020:mrn":{"exact":[],"prefix":["LmjF16.1020:mRNA"]},"lmjf35.snorna.0073":{"exact":[],"prefix":["LmjF35.snoRNA.0073:snoRNA"]},"398024312":{"exact":[["398024312",0,"LmjF.36.1925","LmjF.36",762637,762916]],"prefix":[]},"lmjf33.1895:pe":{"exact":[],"prefix":["LmjF33.1895:pep"]},"chr36_tmp.504":{"exact":[["CHR36_tmp.504",0,"LmjF.36.1140","LmjF.36",429718,430636]],"prefix":[]},"lmjf.30.t120":{"exact":[],"prefix":["LmjF.30.T1200","LmjF.30.T1205"]},"lmjf27.0570":{"exact":[["LmjF27.0570",0,"LmjF.27.0570","LmjF.27",225780,227430]],"prefix":["LmjF27.0570:mRNA","LmjF27.0570:pep"]},"lmjf.13.021":{"exact":[],"prefix":["LmjF.13.0210"]},"157863905":{"exact":[["157863905",0,"LmjF.05.0270","LmjF.05",86240,87200]],"prefix":[]},"lmjf14.0170:mr":{"exact":[],"prefix":["LmjF14.0170:mRNA"]},"lmjf18.1060:mrna":{"exact":[["LmjF18.1060:mRNA",0,"LmjF.18.1060","LmjF.18",450157,452482]],"prefix":[]},"lmjf26.snorna.0108:snorn":{"exact":[],"prefix":["LmjF26.snoRNA.0108:snoRNA"]},"lmjf25.0070:mrna":{"exact":[["LmjF25.0070:mRNA",0,"LmjF.25.0070","LmjF.25",23731,24625]],"prefix":[]},"lmjf35.1190:m":{"exact":[],"prefix":["LmjF35.1190:mRNA"]},"15786491":{"exact":[],"prefix":["157864910","157864912","157864914","157864916","157864918"]},"lmjf.30.t2085":{"exact":[["LmjF.30.T2085",1,"LmjF.30.T2085","LmjF.30",782280,783344]],"prefix":[]},"lmjf36.0360:mr":{"exact":[],"prefix":["LmjF36.0360:mRNA"]},"lmjf33.0840:":{"exact":[],"prefix":["LmjF33.0840:mRNA","LmjF33.0840:pep"]},"lmjf14.0340:m":{"exact":[],"prefix":["LmjF14.0340:mRNA"]},"lmjf04.0980:pep":{"exact":[["LmjF04.0980:pep",0,"LmjF.04.0980","LmjF.04",379215,382821]],"prefix":[]},"lmjf28.2150":{"exact":[["LmjF28.2150",0,"LmjF.28.2150","LmjF.28",836967,839472]],"prefix":["LmjF28.2150:mRNA","LmjF28.2150:pep"]},"lmjchr31_ncrna4:ncr":{"exact":[],"prefix":["Lmjchr31_ncRNA4:ncRNA"]},"lmjf.26.snorna0515":{"exact":[["LmjF.26.snoRNA0515",0,"LmjF.26.snoRNA0515","LmjF.26",651766,651836]],"prefix":[]},"cytoplasmic dynein 2 heavy chain (":{"exact":[],"prefix":["Cytoplasmic dynein 2 heavy chain (DYNC2H2)"]},"98391957":{"exact":[["98391957",0,"LmjF.29.2740","LmjF.29",1169534,1170506]],"prefix":[]},"lmjf34.113":{"exact":[],"prefix":["LmjF34.1130:mRNA","LmjF34.1130","LmjF34.1130:pep"]},"lmjf.18.t038":{"exact":[],"prefix":["LmjF.18.T0380","LmjF.18.T0385"]},"134067641":{"exact":[["134067641",0,"LmjF.09.0930","LmjF.09",367465,367915]],"prefix":[]},"lm5cs1c3":{"exact":[],"prefix":["LM5Cs1C3.1","LM5Cs1C3.2","LM5Cs1C3.3","LM5Cs1C3.4","LM5Cs1C3.5","LM5Cs1C3.6"]},"lmjf.27.221":{"exact":[],"prefix":["LmjF.27.2210"]},"lmjf.28.t1435":{"exact":[["LmjF.28.T1435",1,"LmjF.28.T1435","LmjF.28",543083,543638]],"prefix":[]},"lmjf.36.t18":{"exact":[],"prefix":["LmjF.36.T1800","LmjF.36.T1810","LmjF.36.T1820","LmjF.36.T1825","LmjF.36.T1830","LmjF.36.T1840","LmjF.36.T1850","LmjF.36.T1860","LmjF.36.T1870","LmjF.36.T1880","LmjF.36.T1890"]},"lmjf36.4600:mr":{"exact":[],"prefix":["LmjF36.4600:mRNA"]},"lmjf07.0970:mrn":{"exact":[],"prefix":["LmjF07.0970:mRNA"]},"68124446":{"exact":[["68124446",0,"LmjF.08.1250","LmjF.08",561200,562640]],"prefix":[]},"lmjf28.1590:pep":{"exact":[["LmjF28.1590:pep",0,"LmjF.28.1590","LmjF.28",598395,599676]],"prefix":[]}}