{"lmjf.27.trrna.15-rrna.21":{"exact":[["LmjF.27.TrRNA.15-rRNA.21",1,"LmjF.27.TrRNA.15-rRNA.21","LmjF.27",1020292,1022688]],"prefix":[]},"68128448":{"exact":[["68128448",0,"LmjF.32.0610","LmjF.32",212216,213308]],"prefix":[]},"68125783":{"exact":[["68125783",0,"LmjF.17.0680","LmjF.17",369579,370914]],"prefix":[]},"lmjf.23.108":{"exact":[],"prefix":["LmjF.23.1082","LmjF.23.1080","LmjF.23.1084","LmjF.23.1086","LmjF.23.1088"]},"lmjf.24.t2120":{"exact":[["LmjF.24.T2120",1,"LmjF.24.T2120","LmjF.24",778765,783300]],"prefix":[]},"lmjf20.0560:pep":{"exact":[["LmjF20.0560:pep",0,"LmjF.20.0560","LmjF.20",198149,199931]],"prefix":[]},"lmjf29.2880:pe":{"exact":[],"prefix":["LmjF29.2880:pep"]},"lmjf.18.003":{"exact":[],"prefix":["LmjF.18.0030"]},"lmjf.15.t147":{"exact":[],"prefix":["LmjF.15.T1470"]},"lmjf.36.t1220":{"exact":[["LmjF.36.T1220",1,"LmjF.36.T1220","LmjF.36",451161,454060]],"prefix":[]},"lmjf33.snorna.0008:snorn":{"exact":[],"prefix":["LmjF33.snoRNA.0008:snoRNA"]},"lmjf.33.t009":{"exact":[],"prefix":["LmjF.33.T0090"]},"lmjf32.0450:pe":{"exact":[],"prefix":["LmjF32.0450:pep"]},"lmjf.07.015":{"exact":[],"prefix":["LmjF.07.0150"]},"157864843":{"exact":[["157864843",0,"LmjF.08.1010","LmjF.08",458885,459932]],"prefix":[]},"lmjf.23.1430":{"exact":[["LmjF.23.1430",0,"LmjF.23.1430","LmjF.23",680923,682276]],"prefix":[]},"lmjf23.0590:mrn":{"exact":[],"prefix":["LmjF23.0590:mRNA"]},"lmjf13.1380:mrn":{"exact":[],"prefix":["LmjF13.1380:mRNA"]},"fatty acid thio":{"exact":[],"prefix":["fatty acid thiokinase (long chain)"]},"lmjf35.1090":{"exact":[["LmjF35.1090",0,"LmjF.35.1090","LmjF.35",499380,502530]],"prefix":["LmjF35.1090:pep","LmjF35.1090:mRNA"]},"lmjf.30.t3340":{"exact":[["LmjF.30.T3340",1,"LmjF.30.T3340","LmjF.30",1258869,1259717]],"prefix":[]},"lmjf05.0290:mrna":{"exact":[["LmjF05.0290:mRNA",0,"LmjF.05.0290","LmjF.05",92359,93817]],"prefix":[]},"lmjf.18.1010":{"exact":[["LmjF.18.1010",0,"LmjF.18.1010","LmjF.18",417662,418001]],"prefix":[]},"32249458":{"exact":[],"prefix":["322494589"]},"lmjf10.0640:pe":{"exact":[],"prefix":["LmjF10.0640:pep"]},"lmjf31.0910:mr":{"exact":[],"prefix":["LmjF31.0910:mRNA"]},"lmjf34.3230:":{"exact":[],"prefix":["LmjF34.3230:mRNA","LmjF34.3230:pep"]},"lmjf21.1500":{"exact":[["LmjF21.1500",0,"LmjF.21.1500","LmjF.21",613017,614730]],"prefix":["LmjF21.1500:mRNA","LmjF21.1500:pep"]},"lmjf.33.215":{"exact":[],"prefix":["LmjF.33.2150"]},"lmjf20.127":{"exact":[],"prefix":["LmjF20.1270:mRNA","LmjF20.1270:pep","LmjF20.1270"]},"lmjf29.2770:":{"exact":[],"prefix":["LmjF29.2770:pep","LmjF29.2770:mRNA"]},"lmjf.32.t314":{"exact":[],"prefix":["LmjF.32.T3140"]},"lmjf11.5srrna.":{"exact":[],"prefix":["LmjF11.5SRRNA.01","LmjF11.5SRRNA.01:rRNA","LmjF11.5SRRNA.02","LmjF11.5SRRNA.02:rRNA","LmjF11.5SRRNA.03","LmjF11.5SRRNA.03:rRNA"]},"15787754":{"exact":[],"prefix":["157877542","157877544","157877546","157877548","157877540"]},"lmjf.22.t0040":{"exact":[["LmjF.22.T0040",1,"LmjF.22.T0040","LmjF.22",13827,14837]],"prefix":[]},"lmjf26.1990:":{"exact":[],"prefix":["LmjF26.1990:pep","LmjF26.1990:mRNA"]},"lmjf36.6200:":{"exact":[],"prefix":["LmjF36.6200:pep","LmjF36.6200:mRNA"]}}